README.md
setup.cfg
setup.py
pyTSI/TSIClient.py
pyTSI/__init__.py
pyTSI/exceptions.py
pyTSI.egg-info/PKG-INFO
pyTSI.egg-info/SOURCES.txt
pyTSI.egg-info/dependency_links.txt
pyTSI.egg-info/requires.txt
pyTSI.egg-info/top_level.txt
pyTSI/common/__init__.py
pyTSI/common/common_funcs.py
pyTSI/environment/__init__.py
pyTSI/environment/environment.py
pyTSI/environment/environment_api.py
pyTSI/hierarchies/__init__.py
pyTSI/hierarchies/hierarchies_api.py
pyTSI/instance_types/Type.py
pyTSI/instance_types/Types.py
pyTSI/instance_types/__init__.py
pyTSI/instances/TimeSeries.py
pyTSI/instances/TimeSeriesInstance.py
pyTSI/instances/__init__.py
pyTSI/variables/Variable.py
pyTSI/variables/__init__.py