Metadata-Version: 2.1
Name: pyTSI
Version: 0.3.2
Summary: UNKNOWN
Home-page: https://gitlab.com/josebagar/pytsi/
Author: Joseba Echevarría García
Author-email: joseba.gar@gmail.com
License: MIT
Download-URL: https://gitlab.com/josebagar/pytsi/-/releases/pyTSI_0.3.2
Keywords: Time Series Insight,TSI,TSI SDK
Platform: UNKNOWN
Classifier: Development Status :: 3 - Alpha
Classifier: Intended Audience :: Developers
Classifier: Topic :: Software Development :: Build Tools
Classifier: License :: OSI Approved :: MIT License
Classifier: Programming Language :: Python :: 3.7
